uloger/__init__.py
uloger/uloger.py
uloger-0.1.3.dist-info/METADATA
uloger-0.1.3.dist-info/WHEEL
uloger-0.1.3.dist-info/top_level.txt
uloger-0.1.3.dist-info/RECORD
