Metadata-Version: 2.4
Name: uloger
Version: 0.1.3
Summary: 一个灵活的Python日志辅助模块
Home-page: https://gitcode.com/pymod/uloger
Author: pymod
Author-email: pymod <pymod@example.com>
License: MIT
Project-URL: Homepage, https://gitcode.com/pymod/uloger
Project-URL: Repository, https://gitcode.com/pymod/uloger
Classifier: Development Status :: 4 - Beta
Classifier: Intended Audience :: Developers
Classifier: License :: OSI Approved :: MIT License
Classifier: Programming Language :: Python :: 3
Classifier: Programming Language :: Python :: 3.6
Classifier: Programming Language :: Python :: 3.7
Classifier: Programming Language :: Python :: 3.8
Classifier: Programming Language :: Python :: 3.9
Classifier: Programming Language :: Python :: 3.10
Requires-Python: >=3.6
Provides-Extra: dev
Requires-Dist: pytest>=6.0; extra == "dev"
Requires-Dist: pytest-cov; extra == "dev"
Requires-Dist: black>=21.0b1; extra == "dev"
Requires-Dist: flake8; extra == "dev"
Dynamic: author
Dynamic: home-page
Dynamic: requires-python
